companion/__init__.py
companion/enums.py
companion/handler.py
companion/parser.py
companion/request.py
companion/response.py
companion/server.py
companion_server-1.3.3.dist-info/LICENSE
companion_server-1.3.3.dist-info/METADATA
companion_server-1.3.3.dist-info/WHEEL
companion_server-1.3.3.dist-info/entry_points.txt
companion_server-1.3.3.dist-info/RECORD
