Metadata-Version: 2.3
Name: companion-server
Version: 1.3.3
Summary: a basic http 1.0 server implemented in python
License: MIT License
Author: dankrzeminski32
Author-email: dankrzeminski32@gmail.com
Requires-Python: >=3.11, <4
Classifier: License :: Other/Proprietary License
Classifier: Programming Language :: Python :: 3
Classifier: Programming Language :: Python :: 3.11
Classifier: Programming Language :: Python :: 3.12
Classifier: Programming Language :: Python :: 3.13
Project-URL: Repository, https://github.com/dankrzeminski32/companion
